AUTHORS.rst
CONTRIBUTING.rst
HISTORY.rst
LICENSE
MANIFEST.in
README.rst
setup.cfg
setup.py
docs/Makefile
docs/authors.rst
docs/conf.py
docs/contributing.rst
docs/history.rst
docs/index.rst
docs/installation.rst
docs/make.bat
docs/readme.rst
docs/usage.rst
pygear/__init__.py
pygear/cli.py
pygear/pygear.py
pygear.egg-info/PKG-INFO
pygear.egg-info/SOURCES.txt
pygear.egg-info/dependency_links.txt
pygear.egg-info/entry_points.txt
pygear.egg-info/not-zip-safe
pygear.egg-info/requires.txt
pygear.egg-info/top_level.txt
tests/__init__.py
tests/test_pygear.py