Metadata-Version: 1.1
Name: pygear
Version: 0.1.0
Summary: PyGear is a collection of useful functions and snippets that you need or could use every day.
Home-page: https://github.com/amir-khakshour/pygear
Author: Amir Khakshour
Author-email: khakshour.amir@gmail.com
License: GNU General Public License v3
Keywords: pygear
Platform: UNKNOWN
Classifier: Development Status :: 2 - Pre-Alpha
Classifier: Intended Audience :: Developers
Classifier: Natural Language :: English
Classifier: Programming Language :: Python :: 2
Classifier: Programming Language :: Python :: 2.6
Classifier: Programming Language :: Python :: 2.7
Classifier: Programming Language :: Python :: 3
Classifier: Programming Language :: Python :: 3.3
Classifier: Programming Language :: Python :: 3.4
Classifier: Programming Language :: Python :: 3.5
